{
    "spelling": [
        "/ədˈhɪr/"
    ],
    "synonyms": [
        "comply",
        "bond",
        "observe",
        "adhesive",
        "follower"
    ],
    "meaning": [
        {
            "pos": "verb",
            "en": "To stick fast; stay attached.",
            "vi": "Để dính nhanh; lưu luyến."
        }
    ],
    "sentences": [
        {
            "en": "All drivers must adhere to speed limits.",
            "vi": "Tất cả người lái xe phải tuân thủ giới hạn tốc độ."
        },
        {
            "en": "It is wise to adhere to the rules of your parents.",
            "vi": "Điều khôn ngoan là tuân thủ các quy tắc của cha mẹ bạn."
        }
    ],
    "words_form": [
        "adhered",
        "adheres",
        "adhering"
    ],
    "meaning_vi": "tuân thủ"
}