{
    "spelling": [
        "/əˈɡri/"
    ],
    "synonyms": [
        "assent",
        "correspond",
        "concur",
        "agree",
        "acquiesce"
    ],
    "meaning": [
        {
            "pos": "verb",
            "en": "To grant or concede.",
            "vi": "Để cấp hoặc thừa nhận."
        }
    ],
    "sentences": [
        {
            "en": "We both agree that you need to get out of this place for a while.",
            "vi": "Cả hai chúng tôi đều đồng ý rằng bạn cần phải rời khỏi nơi này một thời gian."
        },
        {
            "en": "I agree with you.",
            "vi": "Tôi đồng ý với bạn."
        }
    ],
    "words_form": [
        "agreed",
        "agreeing",
        "agrees"
    ],
    "meaning_vi": "đồng ý, tán thành"
}