{
    "spelling": [
        "/ˈɑːgjʊəbli/"
    ],
    "synonyms": [],
    "meaning": [
        {
            "pos": "adverb",
            "en": "As can be supported by argument.",
            "vi": "Theo ấn tượng dễ thấy của ai đó (có thể bị cáo buộc sau đó)."
        }
    ],
    "sentences": [
        {
            "en": "Arguably, the most powerful storyline moments on Grey's Anatomy were spoiled including the death of Denny (Jeffrey Dean Morgan) after surviving the latter half of the second season and the cut LVAT wire.",
            "vi": "Có thể cho rằng, những khoảnh khắc cốt truyện mạnh mẽ nhất trên Grey's Anatomy đã bị hỏng bao gồm cái chết của Denny (Jeffrey Dean Morgan) sau khi sống sót ở nửa sau của mùa thứ hai và sợi dây LVAT bị cắt."
        },
        {
            "en": "This hugely symbolic event was arguably a ritual act of public desecration which transgressed the most sacred site of communist public space.",
            "vi": "Sự kiện cực kỳ mang tính biểu tượng này được cho là một hành động mang tính nghi lễ xúc phạm nơi công cộng đã xâm phạm địa điểm thiêng liêng nhất của không gian công cộng cộng sản."
        }
    ],
    "words_form": [],
    "meaning_vi": [
        {
            "pos": "adverb",
            "en": "As can be supported by argument.",
            "vi": "Theo ấn tượng dễ thấy của ai đó (có thể bị cáo buộc sau đó)."
        }
    ]
}