{
    "spelling": [
        "/bɛɡ/"
    ],
    "synonyms": [
        "solicit",
        "pray for",
        "request",
        "ask",
        "crave"
    ],
    "meaning": [
        {
            "pos": "verb",
            "en": "The definition of beg means to plead for something, especially for money or assistance.",
            "vi": "Định nghĩa về cầu xin có nghĩa là cầu xin một điều gì đó, đặc biệt là xin tiền hoặc sự giúp đỡ."
        },
        {
            "pos": "noun",
            "en": "A provincial governor under the Ottoman Empire, a bey.",
            "vi": "Một thống đốc cấp tỉnh dưới thời Đế chế Ottoman, một người đáng yêu."
        },
        {
            "pos": "abbreviation",
            "en": "(knitting) Beginning.",
            "vi": "(đan) Bắt đầu."
        },
        {
            "pos": "idiom",
            "en": "beg (someone's) pardon  Used to introduce a polite request.",
            "vi": "xin (của ai đó) pardon Dùng để giới thiệu một yêu cầu lịch sự."
        }
    ],
    "sentences": [
        {
            "en": "I beg your pardon.",
            "vi": "Tôi cầu xin sự tha thứ của bạn."
        },
        {
            "en": "If I want anything, I won't beg--I'll take it!",
            "vi": "Nếu tôi muốn bất cứ điều gì, tôi sẽ không cầu xin - Tôi sẽ lấy nó!"
        }
    ],
    "words_form": [
        "begged",
        "begging",
        "begs"
    ],
    "meaning_vi": "ăn xin"
}