{
    "spelling": [
        "/ˈbɔɪˌfrɛnd/"
    ],
    "synonyms": [
        "beau",
        "girlfriend",
        "date",
        "ex-husband",
        "fellow"
    ],
    "meaning": [
        {
            "pos": "noun",
            "en": "A sweetheart who is a boy or man.",
            "vi": "Người yêu là con trai hay đàn ông."
        }
    ],
    "sentences": [
        {
            "en": "I don't have a boyfriend.",
            "vi": "Tôi không có bạn trai."
        },
        {
            "en": "Her biggest problem now would be explaining things to her boyfriend, who was probably still nursing his wounds.",
            "vi": "Vấn đề lớn nhất của cô bây giờ là giải thích mọi chuyện với bạn trai, người có lẽ vẫn đang điều trị vết thương."
        }
    ],
    "words_form": [
        "boyfriends"
    ],
    "meaning_vi": "bạn trai"
}