{
    "spelling": [
        "/kəmˈpænjən/"
    ],
    "synonyms": [
        "partner",
        "friend",
        "accompaniment",
        "concomitant",
        "matron"
    ],
    "meaning": [
        {
            "pos": "noun",
            "en": "The definition of a companion is a partner to, friend who accompanies, mate or someone hired to help another.",
            "vi": "Định nghĩa về một người bạn đồng hành là một đối tác, bạn bè đi cùng, bạn đời hoặc một người nào đó được thuê để giúp đỡ người khác."
        },
        {
            "pos": "verb",
            "en": "To be a companion to; accompany.",
            "vi": "Là một người bạn đồng hành với; đồng hành."
        }
    ],
    "sentences": [
        {
            "en": "She gave her companion an angry glance.",
            "vi": "Cô giận dữ liếc nhìn người bạn đồng hành của mình."
        },
        {
            "en": "\"Are you taking me as your companion?\" she asked.",
            "vi": "\"Anh đang coi em là bạn đồng hành của anh sao?\" cô ấy hỏi."
        }
    ],
    "words_form": [
        "companions"
    ],
    "meaning_vi": "đồng hành"
}