{
    "spelling": [
        "/kənˈfɛʃən/"
    ],
    "synonyms": [
        "acknowledgment",
        "admission",
        "assertion",
        "concession",
        "disclosure"
    ],
    "meaning": [
        {
            "pos": "noun",
            "en": "An avowal of belief in the doctrines of a particular faith; a creed.",
            "vi": "Chất lượng hoặc tình trạng phức tạp."
        },
        {
            "pos": "",
            "en": "A confession induced by the police or other law enforcement officers’ use of coercion, deceit, promises, or psychological pressure.",
            "vi": "Hành động, quá trình hoặc sức mạnh của việc thụ thai về mặt tinh thần; hình thành ý tưởng, đặc biệt. của sự trừu tượng."
        }
    ],
    "sentences": [
        {
            "en": "The confession consisted of forty articles.",
            "vi": "Tâm sự gồm có bốn mươi bài."
        },
        {
            "en": "Startled by the confession, Jessi rested her elbows on the table and leaned forward.",
            "vi": "Giật mình trước lời tỏ tình, Jessi chống khuỷu tay lên bàn và rướn người về phía trước."
        }
    ],
    "words_form": [],
    "meaning_vi": [
        {
            "pos": "noun",
            "en": "An avowal of belief in the doctrines of a particular faith; a creed.",
            "vi": "Chất lượng hoặc tình trạng phức tạp."
        },
        {
            "pos": "",
            "en": "A confession induced by the police or other law enforcement officers’ use of coercion, deceit, promises, or psychological pressure.",
            "vi": "Hành động, quá trình hoặc sức mạnh của việc thụ thai về mặt tinh thần; hình thành ý tưởng, đặc biệt. của sự trừu tượng."
        }
    ]
}