{
    "spelling": [
        "/ˈkɑn(t)ʃəns/"
    ],
    "synonyms": [
        "compunction",
        "immorality",
        "inner voice",
        "heart",
        "psyche"
    ],
    "meaning": [
        {
            "pos": "noun",
            "en": "(obsolete) Consciousness or awareness of something.",
            "vi": "(lỗi thời) Ý thức hoặc nhận thức về một cái gì đó."
        },
        {
            "pos": "idiom",
            "en": "in (all good) conscience  In all fairness; by any reasonable standard.",
            "vi": "trong (tất cả tốt) lương tâm Trong tất cả sự công bằng; theo bất kỳ tiêu chuẩn hợp lý nào."
        }
    ],
    "sentences": [
        {
            "en": "He did the task for the sake of his conscience.",
            "vi": "Anh đã làm nhiệm vụ vì lương tâm của mình."
        },
        {
            "en": "His fine character and conscience earned him universal respect and confidence.",
            "vi": "Tính cách và lương tâm tốt đẹp của anh ấy đã khiến anh ấy được mọi người tôn trọng và tin tưởng."
        }
    ],
    "words_form": [],
    "meaning_vi": "lương tâm"
}