{
    "spelling": [
        "/kəlt/"
    ],
    "synonyms": [
        "clique",
        "ritual",
        "veneration",
        "sect",
        "mythological"
    ],
    "meaning": [
        {
            "pos": "noun",
            "en": "The definition of a cult is a group of people with extreme dedication to a certain leader or set of beliefs that are often viewed as odd by others, or is an excessive and misplaced admiration for someone or something, or is something that is popular among a certain segment of society.",
            "vi": "Định nghĩa về một sự sùng bái là một nhóm người có sự cống hiến hết mình cho một nhà lãnh đạo hoặc tập hợp niềm tin nào đó thường bị người khác coi là kỳ quặc, hoặc là sự ngưỡng mộ quá mức và không đúng chỗ đối với ai đó hoặc điều gì đó hoặc là thứ gì đó phổ biến trong số một một bộ phận nào đó của xã hội."
        },
        {
            "pos": "adjective",
            "en": "Enjoyed by a small, loyal group.",
            "vi": "Rất thích bởi một nhóm nhỏ, trung thành."
        }
    ],
    "sentences": [
        {
            "en": "There's an active cult in the area.",
            "vi": "Có một giáo phái đang hoạt động trong khu vực."
        },
        {
            "en": "The cult of the Baal of Tyre followed Jezebel to the royal city Samaria and even found its way into Jerusalem.",
            "vi": "Sự sùng bái Ba-anh-lốp đã theo Giê-ru-sa-lem đến thành phố hoàng gia Sa-ma-ri và thậm chí tìm đường vào Giê-ru-sa-lem."
        }
    ],
    "words_form": [
        "cults"
    ],
    "meaning_vi": "sùng bái"
}