{
    "spelling": [
        "/ˌdɛkəˈreɪʃ(ə)n/"
    ],
    "synonyms": [
        "adornment",
        "interior-decoration",
        "ornamentation",
        "enrichment",
        "reward"
    ],
    "meaning": [
        {
            "pos": "noun",
            "en": "The definition of a decoration is an item used to make a room or thing more beautiful, or a medal given as an awarding.",
            "vi": "Định nghĩa về đồ trang trí là một vật dụng được sử dụng để làm đẹp hơn cho căn phòng hoặc vật dụng, hoặc một huy chương được trao như một phần thưởng."
        }
    ],
    "sentences": [
        {
            "en": "The new decoration of the Premises contributed much to the magnificence of the spectacle.",
            "vi": "Trang trí mới của Mặt bằng đã góp phần không nhỏ vào sự tráng lệ của cảnh tượng."
        },
        {
            "en": "It is therefore probable that most if not all of the sculptural decoration of the Parthenon was the work of pupils of Pheidias, such as Alcamenes and Agoracritus, rather than his own.",
            "vi": "Do đó, có thể xảy ra rằng hầu hết nếu không phải tất cả các trang trí điêu khắc của Parthenon là tác phẩm của các học trò của Pheidias, chẳng hạn như Alcamenes và Agoracritus, chứ không phải của riêng anh ta."
        }
    ],
    "words_form": [
        "decorations"
    ],
    "meaning_vi": "trang trí"
}