{
    "spelling": [
        "/dɑt/"
    ],
    "synonyms": [
        "spot",
        "period",
        "tittle",
        "umlaut",
        "mark"
    ],
    "meaning": [
        {
            "pos": "noun",
            "en": "The definition of a dot is a very small spot or mark or a spot, period or mark used in letters or for punctuation.",
            "vi": "Định nghĩa về dấu chấm là một điểm hoặc dấu rất nhỏ hoặc một dấu chấm, dấu chấm hoặc dấu được sử dụng trong các chữ cái hoặc dấu câu."
        },
        {
            "pos": "verb",
            "en": "To mark with a dot.",
            "vi": "Để đánh dấu bằng dấu chấm."
        },
        {
            "pos": "abbreviation",
            "en": "Department of Transportation.",
            "vi": "Sở Giao thông vận tải."
        },
        {
            "pos": "pronoun",
            "en": "Diminutive of the female given name Dorothy.",
            "vi": "Nhỏ bé của người phụ nữ được đặt tên Dorothy."
        },
        {
            "pos": "idiom",
            "en": "dot (one's) i's  To be thorough or painstaking in attending to details.",
            "vi": "dấu chấm (một người) tôi Là người kỹ lưỡng hoặc chăm chỉ tham gia vào các chi tiết."
        }
    ],
    "sentences": [
        {
            "en": "Dean pointed to a small dot midpoint on the page.",
            "vi": "Dean chỉ vào một điểm giữa chấm nhỏ trên trang giấy."
        },
        {
            "en": "At 3:00 pm on the dot, Sam arrived at the door for her interview.",
            "vi": "Vào lúc 3 giờ chiều, Sam đến cửa để phỏng vấn."
        }
    ],
    "words_form": [
        "dots",
        "dotted",
        "dotting"
    ],
    "meaning_vi": "dấu chấm"
}