{
    "spelling": [
        "/ˈɪndəstri/"
    ],
    "synonyms": [
        "patience",
        "diligence",
        "assiduity",
        "persistence",
        "manufacturing"
    ],
    "meaning": [
        {
            "pos": "noun",
            "en": "Systematic work; habitual employment.",
            "vi": "Làm việc có hệ thống; việc làm theo thói quen."
        }
    ],
    "sentences": [
        {
            "en": "He was at a place in the industry where he did what he pleased.",
            "vi": "Anh ấy đã ở một vị trí trong ngành, nơi anh ấy làm những gì anh ấy hài lòng."
        },
        {
            "en": "The mass food industry of today cannot make this claim.",
            "vi": "Ngành công nghiệp thực phẩm đại chúng ngày nay không thể đưa ra yêu cầu này."
        }
    ],
    "words_form": [
        "industries"
    ],
    "meaning_vi": "công nghiệp"
}