{
    "spelling": [
        "/ˈlɔɪ(ə)l/"
    ],
    "synonyms": [
        "faithful",
        "dependable",
        "true-blue",
        "slavish",
        "true"
    ],
    "meaning": [
        {
            "pos": "adjective",
            "en": "The definition of loyal is faithful or showing faithfulness to a government, person or cause.",
            "vi": "Định nghĩa của trung thành là trung thành hoặc thể hiện sự trung thành với chính phủ, cá nhân hoặc chính nghĩa."
        },
        {
            "pos": "pronoun",
            "en": "A city in Wisconsin.",
            "vi": "Một thành phố ở Wisconsin."
        }
    ],
    "sentences": [
        {
            "en": "She was brilliant, loyal, and sweet.",
            "vi": "Cô ấy tuyệt vời, trung thành và ngọt ngào."
        },
        {
            "en": "Elise had been loyal enough to help her.",
            "vi": "Elise đã đủ trung thành để giúp cô ấy."
        }
    ],
    "words_form": [],
    "meaning_vi": "trung thành"
}