{
    "spelling": [
        "/ˈpɔɪn(t)əd/"
    ],
    "synonyms": [
        "tart",
        "sharp",
        "fine",
        "spiked",
        "acuminate"
    ],
    "meaning": [
        {
            "pos": "adjective",
            "en": "Having an end coming to a point.",
            "vi": "Có một kết thúc đến một điểm."
        },
        {
            "pos": "verb",
            "en": "Simple past tense and past participle of point.",
            "vi": "Thì quá khứ đơn và quá khứ phân từ của điểm."
        }
    ],
    "sentences": [
        {
            "en": "He pointed to a blossoming rainbow.",
            "vi": "Anh chỉ vào một cầu vồng đang nở."
        },
        {
            "en": "She needs certain facts pointed out to her.",
            "vi": "Cô ấy cần những sự thật nhất định được chỉ ra cho cô ấy."
        }
    ],
    "words_form": [],
    "meaning_vi": "chỉ"
}