{
    "spelling": [
        "/ˈridʒən/"
    ],
    "synonyms": [
        "territory",
        "area",
        "sector",
        "country",
        "section"
    ],
    "meaning": [
        {
            "pos": "noun",
            "en": "An area; place; space.",
            "vi": "Một khu vực; địa điểm; không gian."
        }
    ],
    "sentences": [
        {
            "en": "In its earlier history the region was agricultural.",
            "vi": "Trong lịch sử trước đây của nó, khu vực này là nông nghiệp."
        },
        {
            "en": "If you travel to a different region, you may find an idiom that you don't understand.",
            "vi": "Nếu bạn đi du lịch đến một vùng khác, bạn có thể tìm thấy một thành ngữ mà bạn không hiểu."
        }
    ],
    "words_form": [
        "regions"
    ],
    "meaning_vi": "vùng"
}