{
    "spelling": [
        "/səˈsaɪədi/"
    ],
    "synonyms": [
        "community",
        "nation",
        "friendship",
        "aristocracy",
        "upper class"
    ],
    "meaning": [
        {
            "pos": "noun",
            "en": "Society is defined as a group of people living as a community or an organized group of people for a common purpose.",
            "vi": "Xã hội được định nghĩa là một nhóm người sống như một cộng đồng hoặc một nhóm người có tổ chức vì một mục đích chung."
        },
        {
            "pos": "adjective",
            "en": "The definition of society is anything relating to the fashionable or wealthy community.",
            "vi": "Định nghĩa về xã hội là bất cứ thứ gì liên quan đến cộng đồng thời thượng hoặc giàu có."
        }
    ],
    "sentences": [
        {
            "en": "I thought maybe I wasn't high society material.",
            "vi": "Tôi nghĩ có lẽ tôi không có vật chất cao trong xã hội."
        },
        {
            "en": "He had a brilliant position in society thanks to his intimacy with Countess Bezukhova, a brilliant position in the service thanks to the patronage of an important personage whose complete confidence he enjoyed, and he was beginning to make plans for marrying one of the richest heiresses in Petersburg, plans which might very easily be realized.",
            "vi": "Anh ta đã có một vị trí sáng giá trong xã hội nhờ sự thân thiết của mình với Nữ bá tước Bezukhova, một vị trí sáng giá trong dịch vụ nhờ sự bảo trợ của một nhân vật quan trọng mà anh ta hoàn toàn tự tin, và anh ta đang bắt đầu lên kế hoạch kết hôn với một trong những người thừa kế giàu có nhất. Petersburg, những kế hoạch có thể rất dễ dàng thành hiện thực."
        }
    ],
    "words_form": [
        "societies"
    ],
    "meaning_vi": "xã hội"
}