{
    "spelling": [
        "/spɔrt/"
    ],
    "synonyms": [
        "gambler",
        "game",
        "play",
        "revelry",
        "athletics"
    ],
    "meaning": [
        {
            "pos": "adjective",
            "en": "Sport means something used for athletic activities.",
            "vi": "Thể thao có nghĩa là một cái gì đó được sử dụng cho các hoạt động thể thao."
        },
        {
            "pos": "noun",
            "en": "(obsolete) Amorous dalliance; lovemaking.",
            "vi": "(lỗi thời) Đa tình; làm tình."
        },
        {
            "pos": "verb",
            "en": "To wear or have on one's body, especially prominently or ostentatiously.",
            "vi": "Để mặc hoặc có trên cơ thể của một người, đặc biệt là nổi bật hoặc phô trương."
        },
        {
            "pos": "acronym",
            "en": "Strategic Partnership On REACH Testing.",
            "vi": "Quan hệ đối tác chiến lược về thử nghiệm REACH."
        },
        {
            "pos": "idiom",
            "en": "in sport  in joke or jest; not in earnest",
            "vi": "trong thể thao trong trò đùa hoặc trò đùa; không nghiêm túc"
        }
    ],
    "sentences": [
        {
            "en": "You be there to show her what a good sport you are.",
            "vi": "Bạn ở đó để cho cô ấy thấy bạn là một môn thể thao tốt."
        },
        {
            "en": "There remained a second rope, various books on the sport of ice climbing and a few pitons.",
            "vi": "Vẫn còn một sợi dây thứ hai, nhiều cuốn sách khác nhau về môn thể thao leo núi và một vài chiếc piton."
        }
    ],
    "words_form": [
        "sported",
        "sporting",
        "sports"
    ],
    "meaning_vi": "thể thao"
}