{
    "spelling": [
        "/ˌəndərˈɡoʊ/"
    ],
    "synonyms": [
        "feel",
        "go through",
        "support",
        "bear",
        "have"
    ],
    "meaning": [
        {
            "pos": "verb",
            "en": "To undergo is to experience something.",
            "vi": "Trải qua là trải nghiệm một cái gì đó."
        }
    ],
    "sentences": [
        {
            "en": "Its tendency to undergo cyclical changes.",
            "vi": "Xu hướng của nó thay đổi theo chu kỳ."
        },
        {
            "en": "They live for some time in water or mud, occasionally entering the bodies of water snails, but undergo no change until they reach the lung of a frog, when the cycle begins anew.",
            "vi": "Chúng sống một thời gian trong nước hoặc bùn, đôi khi xâm nhập vào cơ thể của ốc sên nước, nhưng không thay đổi cho đến khi chúng đến phổi của ếch, khi chu kỳ bắt đầu lại."
        }
    ],
    "words_form": [
        "undergoes",
        "undergoing",
        "undergone",
        "underwent"
    ],
    "meaning_vi": "trải qua"
}